html5tagger/__init__.py
html5tagger/builder.py
html5tagger/document.py
html5tagger/html5.py
html5tagger/makebuilder.py
html5tagger/util.py
html5tagger-1.2.1.dist-info/METADATA
html5tagger-1.2.1.dist-info/WHEEL
html5tagger-1.2.1.dist-info/top_level.txt
html5tagger-1.2.1.dist-info/RECORD
