Metadata-Version: 2.1
Name: html5tagger
Version: 1.2.1
Summary: Pythonic HTML generation/templating (no template files)
Home-page: https://github.com/sanic-org/html5tagger
Author: Sanic Community
Author-email: tronic@noreply.users.github.com
Keywords: HTML,HTML5,templating,Jinja2
Classifier: Development Status :: 5 - Production/Stable
Classifier: Intended Audience :: Developers
Classifier: Programming Language :: Python :: 3
Classifier: Programming Language :: Python :: 3.7
Classifier: Programming Language :: Python :: 3.8
Classifier: Programming Language :: Python :: 3.9
Classifier: Programming Language :: Python :: 3.10
Classifier: Programming Language :: Python :: 3.11
Classifier: Topic :: Text Processing :: Markup :: HTML
Classifier: License :: OSI Approved :: MIT License
Classifier: License :: Public Domain
Classifier: Operating System :: OS Independent
Requires-Python: >=3.7
